gospeed_api-3.0.1.dist-info/METADATA
gospeed_api-3.0.1.dist-info/WHEEL
gospeed_api-3.0.1.dist-info/entry_points.txt
gospeed_api/__init__.py
gospeed_api/index.py
gospeed_api/models/__init__.py
gospeed_api/models/continue_a_task.py
gospeed_api/models/continue_all_tasks.py
gospeed_api/models/create_a_batch_of_tasks.py
gospeed_api/models/create_a_task.py
gospeed_api/models/delete_a_task.py
gospeed_api/models/delete_tasks.py
gospeed_api/models/get_server_info.py
gospeed_api/models/get_task_info.py
gospeed_api/models/get_task_list.py
gospeed_api/models/get_task_stats.py
gospeed_api/models/pause_a_task.py
gospeed_api/models/pause_all_tasks.py
gospeed_api/models/resolve_a_request.py
gospeed_api/py.typed
gospeed_api-3.0.1.dist-info/RECORD
