Metadata-Version: 2.1
Name: gospeed-api
Version: 3.0.1
Summary: Default template for PDM package
Author-Email: tick97115115 <32931796+tick97115115@users.noreply.github.com>
License: MIT
Requires-Python: >=3.10
Requires-Dist: pydantic>=2.8.2
Requires-Dist: requests>=2.32.3
Requires-Dist: httpx>=0.27.0
Requires-Dist: trio>=0.26.0
Requires-Dist: anyio>=4.4.0
Requires-Dist: mypy>=1.15.0
